apis_ampel/__init__.py
apis_ampel/admin.py
apis_ampel/apps.py
apis_ampel/fallback_settings.py
apis_ampel/helper_functions.py
apis_ampel/migrations/0001_initial.py
apis_ampel/migrations/0002_auto_20221110_1150.py
apis_ampel/migrations/0003_delete_ampelgeneric.py
apis_ampel/migrations/0004_alter_ampeltemp_temp_entity.py
apis_ampel/migrations/0005_auto_20221111_1022.py
apis_ampel/migrations/__init__.py
apis_ampel/models.py
apis_ampel/template_column.py
apis_ampel/templates/ampel/ampel_documentation.html
apis_ampel/templates/ampel/ampel_edit_template_column.html
apis_ampel/templates/ampel/ampel_inline_template.html
apis_ampel/templates/ampel/ampel_note_column.html
apis_ampel/templates/ampel/ampel_settings_template.html
apis_ampel/templates/ampel/ampel_template_column.html
apis_ampel/templates/ampel/edit_inline_table_column.html
apis_ampel/tests.py
apis_ampel/urls.py
apis_ampel/views.py
apis_ampel-0.2.0.dist-info/WHEEL
apis_ampel-0.2.0.dist-info/METADATA
apis_ampel-0.2.0.dist-info/RECORD
